PolyhedraVolAprox.py
opyrability.py
opyrability-1.4.9.dist-info/LICENSE
opyrability-1.4.9.dist-info/METADATA
opyrability-1.4.9.dist-info/WHEEL
opyrability-1.4.9.dist-info/RECORD
