Metadata-Version: 2.1
Name: opyrability
Version: 1.4.9
Summary: Process operability analysis in Python
License: MIT
Author: Victor Alves
Requires-Python: >=3.9.0,<4.0.0
Classifier: Intended Audience :: End Users/Desktop
Classifier: Intended Audience :: Science/Research
Classifier: License :: OSI Approved :: MIT License
Classifier: Operating System :: MacOS
Classifier: Operating System :: Microsoft :: Windows
Classifier: Operating System :: Unix
Classifier: Programming Language :: Python :: 3
Classifier: Programming Language :: Python :: 3.9
Classifier: Programming Language :: Python :: 3.10
Classifier: Programming Language :: Python :: 3.11
Classifier: Programming Language :: Python :: 3.12
Classifier: Topic :: Scientific/Engineering
Classifier: Topic :: Software Development :: Libraries :: Python Modules
Requires-Dist: cvxopt (>=1.2.7,<2.0.0)
Requires-Dist: jax[cpu] (>=0.4.13,<0.5.0)
Requires-Dist: matplotlib (>=3.6.2,<3.8.0)
Requires-Dist: numpy (>=1.24.1)
Requires-Dist: polytope (>=0.2.4,<0.3.0)
Requires-Dist: scipy (>=1.10.0,<2.0.0)
Requires-Dist: tqdm (>=4.64.1,<5.0.0)
